nema/__init__.py
nema/app/__init__.py
nema/app/app.py
nema/app/utils.py
nema/cli.py
nema/connectivity/__init__.py
nema/connectivity/connectivity_manager.py
nema/data/__init__.py
nema/data/data.py
nema/data/data_properties.py
nema/data/data_type.py
nema/data/distributions/__init__.py
nema/data/distributions/distributions.py
nema/data/linear_algebra/__init__.py
nema/data/linear_algebra/vector.py
nema/data/map_type_to_data_properties.py
nema/data/plots/__init__.py
nema/data/plots/figure_data_properties.py
nema/data/tabular/__init__.py
nema/data/tabular/tabular_data_properties.py
nema/run/__init__.py
nema/run/app.py
nema/run/utils.py
nema/run/workflow.py
nema/utils/__init__.py
nema/utils/create_data_for_workflow.py
nema/utils/file_name.py
nema/utils/global_config.py
nema/utils/units.py
nema/utils/url.py
nema/workflow/__init__.py
nema/workflow/workflow.py
nema-0.1.14.dist-info/METADATA
nema-0.1.14.dist-info/WHEEL
nema-0.1.14.dist-info/entry_points.txt
nema-0.1.14.dist-info/RECORD
