Metadata-Version: 2.3
Name: nema
Version: 0.1.14
Summary: Interact with the Nema data collaboration platform
Author: Max Opgenoord
Author-email: max@nemasystems.io
Requires-Python: >=3.8,<4.0
Classifier: Programming Language :: Python :: 3
Classifier: Programming Language :: Python :: 3.8
Classifier: Programming Language :: Python :: 3.9
Classifier: Programming Language :: Python :: 3.10
Classifier: Programming Language :: Python :: 3.11
Classifier: Programming Language :: Python :: 3.12
Classifier: Programming Language :: Python :: 3.13
Requires-Dist: click (>=8.1.7,<9.0.0)
Requires-Dist: pandas (==2.0.3) ; python_version == "3.8"
Requires-Dist: pandas (>=2.2,<3.0) ; python_version >= "3.9"
Requires-Dist: pint (==0.21.1) ; python_version == "3.8"
Requires-Dist: pint (>=0.24.3,<0.25.0) ; python_version >= "3.9"
Requires-Dist: requests (>=2.32.3,<3.0.0)
Requires-Dist: toml (>=0.10.2,<0.11.0)
